plot_playground/__init__.py
plot_playground/common/__init__.py
plot_playground/common/d3_helper.py
plot_playground/common/data_helper.py
plot_playground/common/img_helper.py
plot_playground/common/js_helper_template_path.py
plot_playground/common/jupyter_helper.py
plot_playground/common/selenium_helper.py
plot_playground/common/settings.py
plot_playground/stats/__init__.py
plot_playground/stats/linux_stats_plot.py
plot_playground/storytelling/__init__.py
plot_playground/storytelling/simple_line_date_series_plot.py
plot_playground/storytelling/slope_plot.py
plot_playground/template/base/d3_exec.html
plot_playground/template/js_helper/get_b_box_width.js
plot_playground/template/js_helper/get_max_width.js
plot_playground/template/stats/linux_stats_plot.css
plot_playground/template/stats/linux_stats_plot.js
plot_playground/template/storytelling/simple_line_date_series_plot.css
plot_playground/template/storytelling/simple_line_date_series_plot.js
plot_playground/template/storytelling/slope_plot.css
plot_playground/template/storytelling/slope_plot.js
plot_playground/tests/__init__.py
plot_playground/tests/test_d3_helper.py
plot_playground/tests/test_data_helper.py
plot_playground/tests/test_img_helper.py
plot_playground/tests/test_jupyter_helper.py
plot_playground/tests/test_linux_stats_plot.py
plot_playground/tests/test_selenium_helper.py
plot_playground/tests/test_settings.py
plot_playground/tests/test_storytelling_simple_line_date_series_plot.py
plot_playground/tests/test_storytelling_slope_plot.py
plot_playground-0.2.1.dist-info/METADATA
plot_playground-0.2.1.dist-info/RECORD
plot_playground-0.2.1.dist-info/WHEEL
plot_playground-0.2.1.dist-info/top_level.txt
